{
  "titulo": "Nossa História",
  "subtitulo": "Cada momento ao teu lado vale ouro",
  "dataNamoro": "03/12/2025",
  "mensagem": "Para a minha marrentinha, com todo o amor do mundo. Feliz aniversário de namoro! 💕",
  "dias": [
    {
      "data": "2025-11-07",
      "titulo": "Nossa Primeira foto comendo docinhos",
      "fotos": [
        "IMG_1048.jpeg",
        "IMG_1049.jpeg",
        "IMG_1050.jpeg",
        "IMG_1051.jpeg",
        "IMG_1052 (1).jpeg",
        "IMG_1052.jpeg"
      ]
    },
    {
      "data": "2025-11-24",
      "titulo": "Uma das, se não a nossa primeira ligação",
      "fotos": [
        "IMG_1231.PNG"
      ]
    },
    {
      "data": "2025-12-03",
      "titulo": "Nosso Pedido de Namoro",
      "fotos": [
        "IMG_1317.jpeg",
        "IMG_1319.jpeg",
        "IMG_1321.jpeg",
        "IMG_1322.jpeg",
        "IMG_1323.jpeg",
        "IMG_1324.jpeg",
        "IMG_1325.jpeg",
        "IMG_1326.jpeg",
        "IMG_1327.jpeg",
        "IMG_1328.jpeg",
        "IMG_1329.jpeg",
        "IMG_1330.jpeg",
        "IMG_1331.jpeg",
        "IMG_1332.jpeg",
        "IMG_1333.jpeg",
        "IMG_1334.jpeg",
        "IMG_1335.jpeg",
        "IMG_1336.jpeg"
      ]
    },
    {
      "data": "2025-12-04",
      "titulo": "Nossa primeira reconsiliação kkkkk",
      "fotos": [
        "IMG_1346.jpeg",
        "IMG_1347.jpeg",
        "IMG_1348.jpeg",
        "IMG_1349.jpeg",
        "IMG_1350.jpeg",
        "IMG_1352.jpeg"

      ]
    },
    {
      "data": "2025-12-12",
      "titulo": "O dia que a gente comeu quase todo o cardapio do Taisho, temos que ir de novo",
      "fotos": [
        "IMG_1435.jpeg",
        "IMG_1436.jpeg",
        "IMG_1437.jpeg",
        "IMG_1438.jpeg",
        "IMG_1439.jpeg",
        "IMG_1440.jpeg",
        "IMG_1441.jpeg",
        "IMG_1442.jpeg",
        "IMG_1443.jpeg",
        "IMG_1444.jpeg",
        "IMG_1445.jpeg",
        "IMG_1446.jpeg",
        "IMG_1447.jpeg",
        "IMG_1448.jpeg",
        "IMG_1449.jpeg",
        "IMG_1450.jpeg",
        "IMG_1451.jpeg",
        "IMG_1452.jpeg",
        "IMG_1453.jpeg",
        "IMG_1454.jpeg",
        "IMG_1455.jpeg",
        "IMG_1456.jpeg",
        "IMG_1457.jpeg",
        "IMG_1458.jpeg",
        "IMG_1478.jpeg",
        "IMG_1486.jpeg",
        "3E07D4E1-DE9D-469E-8E0A-62F5D0F0B50D.JPG",
        "721E140D-7DE7-42C1-8037-ABA22574A4D6.JPG",
        "B7F6A275-3A32-429C-A129-9EE06CB5C914.JPG"
      ]
    },
    {
      "data": "2025-12-18",
      "titulo": "O dia em que descobrimos umas hamburgueria muitoo boaaaa",
      "fotos": [
        "IMG_1660.PNG",
        "IMG_1661.PNG",
        "IMG_1662.PNG",
        "IMG_1663.PNG",
        "IMG_1664.PNG",
        "IMG_1665.PNG",
        "IMG_1666.PNG",
        "IMG_1667.PNG",
        "IMG_1668.PNG",
        "IMG_1690.jpeg",
        "IMG_1691.jpeg",
        "IMG_1692.jpeg",
        "IMG_1693.jpeg",
        "IMG_1694.jpeg",
        "IMG_1695.jpeg",
        "IMG_1696.jpeg",
        "IMG_1701.jpeg",
        "IMG_1702.jpeg",
        "IMG_1703.jpeg",
        "IMG_1704.jpeg",
        "IMG_1705.jpeg",
        "IMG_1706.jpeg",
        "IMG_1707.jpeg",
        "IMG_1708.jpeg",
        "IMG_1709.jpeg",
        "IMG_1710.jpeg",
        "IMG_1712.jpeg",
        "IMG_1713.jpeg",
        "IMG_1717.jpeg",
        "IMG_1718.jpeg",
        "IMG_1719.jpeg"
      ]
    },
    {
      "data": "2025-12-19",
      "titulo": "O dia que a gente ficou com dor na bunda vendo avatar 3",
      "fotos": [
        "IMG_1730.jpeg"
      ]
    },
    {
      "data": "2025-12-20",
      "titulo": "Pizza em familia apos a apresentação de natal, vc dormindo tava muito fofinhaa",
      "fotos": [
        "IMG_1738.jpeg",
        "IMG_1739.jpeg",
        "IMG_1740.jpeg",
        "IMG_1741.jpeg",
        "IMG_1742.jpeg",
        "IMG_1743.jpeg",
        "IMG_1744.jpeg"
      ]
    },
    {
      "data": "2025-12-25",
      "titulo": "Nosso Natal juntinhos, nesse dia eu tava muitoo nervoso, mas vc me ajudou",
      "fotos": [
        "IMG_1788.jpeg",
        "IMG_1789.jpeg",
        "IMG_1790.jpeg",
        "IMG_1791.jpeg",
        "IMG_1795.jpeg"
      ]
    },
    {
      "data": "2025-12-26",
      "titulo": "Nosso passio do parque com nosso filhinho arteiro",
      "fotos": [
        "IMG_1811.jpeg",
        "IMG_1812.jpeg",
        "IMG_1819.jpeg",
        "IMG_1820.jpeg",
        "IMG_1821.jpeg",
        "IMG_1822.jpeg",
        "IMG_1833.jpeg",
        "IMG_1834.jpeg",
        "1c4aedff-c1b0-4431-a156-cf16e60e2772.JPG",
        "754dcc8f-bdf8-4a74-8ae0-28605a2277da.JPG",
        "7a39a542-6801-4c35-87c1-4ebe5d29998b.JPG",
        "99ff4dcb-423e-4a10-ac03-d7c9305d8e75.MP4",
        "9a42d0fb-370d-4a02-9f1e-ad51a49a01a3.JPG",
        "a16aabc5-5910-4c97-ad98-eb97acf5f781.JPG",
        "4b8fb2bf-2eaa-4fda-91e9-93b9da82a563.JPG",
        "c0a5269a-d0e1-4934-a0f3-fb1b564d592b.JPG",
        "df0c73fd-99c9-4ef7-89cb-bd93b07888fd.MP4"
      ]
    },
    {
      "data": "2026-01-09",
      "titulo": "um leve cochilinho usando meu amorzinho de travesseiro",
      "fotos": [
        "IMG_2057.jpeg"
      ]
    },
    {
      "data": "2026-01-17",
      "titulo": "Nossa primeira viagem juntinhos, a melhor viagem da minha vida",
      "fotos": [
        "IMG_2142.jpeg",
        "IMG_2153.jpeg",
        "IMG_2154.jpeg"
      ]
    },
    {
      "data": "2026-01-20",
      "titulo": "A prova que minha namorada me bajulava com sorvete, muito bommm",
      "fotos": [
        "IMG_2185.jpeg"
      ]
    },
    {
      "data": "2026-01-23",
      "titulo": "Nosso primeiro treino juntooss",
      "fotos": [
        "305712f2-8d11-4cd3-9d7c-ece1977f21c7.jpg",
        "46efeeda-7d73-48ae-b1f7-ee1bcb2b5402.JPG"
      ]
    },
    {
      "data": "2026-01-26",
      "titulo": "Primeira vez que comi na Cacau Show, foi maravilhoso só pelo fato de estar com vc",
      "fotos": [
        "IMG_2240.jpeg",
        "IMG_2241.jpeg",
        "IMG_2243.jpeg",
        "IMG_2244.jpeg"
      ]
    },
    {
      "data": "2026-01-30",
      "titulo": "Uma print escondida hehe",
      "fotos": [
        "IMG_2297.PNG"
      ]
    },
    {
      "data": "2026-02-01",
      "titulo": "Nosso primeiro culto juntos, e nosso piquinique maravilhoso com direito a chuva depois",
      "fotos": [
        "AD833407-1F91-4B4F-83E4-F36E9869FC88.JPG",
        "IMG_2327.jpeg",
        "IMG_2328.jpeg",
        "IMG_2329.jpeg",
        "IMG_2330 (1).jpeg",
        "IMG_2330.jpeg",
        "IMG_2331.jpeg",
        "IMG_2332.jpeg",
        "IMG_2333.jpeg",
        "IMG_2334.jpeg",
        "IMG_2335.jpeg",
        "IMG_2336.jpeg",
        "IMG_2337.jpeg",
        "IMG_2342.jpeg",
        "IMG_2343.jpeg",
        "IMG_2344.jpeg",
        "IMG_2345.jpeg",
        "IMG_2348.jpeg",
        "IMG_2349.jpeg",
        "IMG_2350.jpeg",
        "IMG_2366.jpeg",
        "IMG_2371.jpeg",
        "IMG_2372.jpeg",
        "IMG_2373.jpeg",
        "IMG_2374.jpeg",
        "IMG_2375.jpeg",
        "IMG_2376.jpeg",
        "IMG_2377.jpeg",
        "IMG_2378.jpeg",
        "IMG_2380.jpeg",
        "IMG_2381.jpeg",
        "IMG_2383.jpeg",
        "IMG_2385.jpeg",
        "IMG_2386.jpeg",
        "IMG_2387.jpeg",
        "IMG_2388.jpeg",
        "IMG_2389.jpeg",
        "IMG_2390.jpeg",
        "IMG_2391.jpeg",
        "IMG_2392.jpeg",
        "IMG_2393.jpeg",
        "IMG_2394.jpeg",
        "IMG_2395.jpeg",
        "IMG_2396.jpeg",
        "IMG_2397.jpeg",
        "IMG_2398.jpeg",
        "IMG_2404.jpeg"
      ]
    },
    {
      "data": "2026-02-07",
      "titulo": "O dia que assistimos A Empregada, vc estava maravilhosa com aquele vestido",
      "fotos": [
        "IMG_2492.jpeg",
        "IMG_2493.jpeg",
        "IMG_2494.jpeg",
        "IMG_2495.jpeg",
        "IMG_2496.jpeg",
        "IMG_2497.jpeg",
        "IMG_2498.jpeg",
        "IMG_2499.jpeg",
        "IMG_2500.jpeg",
        "IMG_2501.jpeg",
        "IMG_2508.jpeg",
        "IMG_2509.jpeg",
        "IMG_2510.jpeg",
        "IMG_2511.jpeg",
        "IMG_2512.jpeg",
        "IMG_2513.jpeg",
        "IMG_2517.jpeg",
        "IMG_2518.jpeg",
        "IMG_2519.jpeg"
      ]
    },
    {
      "data": "2026-02-11",
      "titulo": "A saida do nosso quarteto",
      "fotos": [
        "IMG_2568.jpeg",
        "IMG_2569.jpeg",
        "IMG_2570.jpeg",
        "IMG_2572.jpeg"
      ]
    },
    {
      "data": "2026-02-15",
      "titulo": "Nosso sorvetiho antes do culto",
      "fotos": [
        "IMG_2652.jpeg",
        "IMG_2653.jpeg",
        "IMG_2654.jpeg"
      ]
    }
  ]
}